mkdocs_gemini_chat/README.md
mkdocs_gemini_chat/__init__.py
mkdocs_gemini_chat/api.py
mkdocs_gemini_chat/server.py
mkdocs_gemini_chat-0.1.4.dist-info/licenses/LICENSE
mkdocs_gemini_chat-0.1.4.dist-info/METADATA
mkdocs_gemini_chat-0.1.4.dist-info/WHEEL
mkdocs_gemini_chat-0.1.4.dist-info/entry_points.txt
mkdocs_gemini_chat-0.1.4.dist-info/top_level.txt
mkdocs_gemini_chat-0.1.4.dist-info/RECORD
