Metadata-Version: 2.4
Name: mkdocs-gemini-chat
Version: 0.1.4
Summary: A Material for MkDocs plugin that adds a Gemini-powered chat window to documentation pages
Home-page: https://github.com/nolanblevins/mkdocs-gemini-chat
Author: Nolan Blevins
Author-email: 
Project-URL: Bug Reports, https://github.com/nolanblevins/mkdocs-gemini-chat/issues
Project-URL: Source, https://github.com/nolanblevins/mkdocs-gemini-chat
Project-URL: Documentation, https://github.com/nolanblevins/mkdocs-gemini-chat#readme
Classifier: Development Status :: 4 - Beta
Classifier: Intended Audience :: Developers
Classifier: License :: OSI Approved :: MIT License
Classifier: Programming Language :: Python :: 3
Classifier: Programming Language :: Python :: 3.8
Classifier: Programming Language :: Python :: 3.9
Classifier: Programming Language :: Python :: 3.10
Classifier: Programming Language :: Python :: 3.11
Classifier: Framework :: MkDocs
Classifier: Topic :: Documentation
Classifier: Topic :: Software Development :: Documentation
Requires-Python: >=3.8
License-File: LICENSE
Requires-Dist: mkdocs>=1.0.0
Requires-Dist: google-generativeai>=0.3.0
Requires-Dist: fastapi<0.69.0,>=0.68.0
Requires-Dist: uvicorn<0.16.0,>=0.15.0
Requires-Dist: pydantic<2.0.0,>=1.8.0
Requires-Dist: python-dotenv>=0.19.0
Provides-Extra: dev
Requires-Dist: pytest>=6.0; extra == "dev"
Requires-Dist: pytest-asyncio>=0.15.0; extra == "dev"
Requires-Dist: pytest-cov>=2.0; extra == "dev"
Requires-Dist: black>=21.0; extra == "dev"
Requires-Dist: isort>=5.0; extra == "dev"
Requires-Dist: flake8>=3.9; extra == "dev"
Requires-Dist: mypy>=0.910; extra == "dev"
Requires-Dist: httpx>=0.24.0; extra == "dev"
Dynamic: author
Dynamic: classifier
Dynamic: description
Dynamic: description-content-type
Dynamic: home-page
Dynamic: license-file
Dynamic: project-url
Dynamic: provides-extra
Dynamic: requires-dist
Dynamic: requires-python
Dynamic: summary
